generic_vectorizer/__init__.py
generic_vectorizer/__main__.py
generic_vectorizer/log.py
generic_vectorizer/background_workers/embedder.py
generic_vectorizer/client/__init__.py
generic_vectorizer/client/client.py
generic_vectorizer/grpc_server/server.py
generic_vectorizer/grpc_server/interfaces/strategies_pb2.py
generic_vectorizer/grpc_server/interfaces/strategies_pb2.pyi
generic_vectorizer/grpc_server/interfaces/strategies_pb2_grpc.py
generic_vectorizer/grpc_server/servicer/text_embedding.py
generic_vectorizer/strategies/__init__.py
generic_vectorizer/strategies/abstract_strategy.py
generic_vectorizer/strategies/embedding/bge_m3.py
generic_vectorizer/strategies/reranker/flag_reranker.py
generic_vectorizer/typing/__init__.py
generic_vectorizer/typing/bge_embedding.py
generic_vectorizer/typing/reranker.py
generic_vectorizer/vectorizer/__init__.py
generic_vectorizer/vectorizer/vectorizer.py
generic_vectorizer-0.1.0.dist-info/LICENSE
generic_vectorizer-0.1.0.dist-info/METADATA
generic_vectorizer-0.1.0.dist-info/WHEEL
generic_vectorizer-0.1.0.dist-info/entry_points.txt
generic_vectorizer-0.1.0.dist-info/top_level.txt
generic_vectorizer-0.1.0.dist-info/RECORD
