Metadata-Version: 2.1
Name: generic_vectorizer
Version: 0.1.0
Summary: A high-performance, distributed text embedding and reranking system based on FlagEmbedding
Author-email: Ibrahima Khalil BA <ibrahima.elmokhtar@gmail.com>
License: MIT License
Project-URL: Homepage, https://github.com/milkymap/generic-vectorizer
Keywords: embedding,reranking,nlp,machine learning,bge-m3
Classifier: License :: OSI Approved :: MIT License
Classifier: Programming Language :: Python
Classifier: Programming Language :: Python :: 3
Requires-Python: >=3.8
License-File: LICENSE
Requires-Dist: click
Requires-Dist: pyzmq
Requires-Dist: grpcio-tools
Requires-Dist: FlagEmbedding
Requires-Dist: pydantic
Requires-Dist: peft
Provides-Extra: dev
Requires-Dist: pytest; extra == "dev"
